quick_tts_mcp/__init__.py
quick_tts_mcp/server.py
quick_tts_mcp/tools.py
quick_tts_mcp-0.1.4.dist-info/METADATA
quick_tts_mcp-0.1.4.dist-info/WHEEL
quick_tts_mcp-0.1.4.dist-info/entry_points.txt
quick_tts_mcp-0.1.4.dist-info/RECORD
