Metadata-Version: 2.4
Name: quick-tts-mcp
Version: 0.1.4
Summary: MCP server providing text-to-speech functionality using OpenAI's API
Project-URL: Homepage, https://github.com/diogoseca/quick-tts-mcp
Project-URL: Repository, https://github.com/diogoseca/quick-tts-mcp
Author-email: Diogo Seca <diogoseca@users.noreply.github.com>
License: MIT
Requires-Python: >=3.8
Requires-Dist: mcp>=1.0.0
Requires-Dist: python-dotenv>=1.1.0
Requires-Dist: quick-tts>=0.1.2
